{  
   "points":[  
      {  
         "x":127.083328,
         "y":186.666656
      },
      {  
         "x":127.083328,
         "y":184.583328
      },
      {  
         "x":127.083328,
         "y":183.750000
      },
      {  
         "x":127.500000,
         "y":183.333328
      },
      {  
         "x":127.500000,
         "y":182.083328
      },
      {  
         "x":127.083328,
         "y":181.666656
      },
      {  
         "x":127.083328,
         "y":181.250000
      },
      {  
         "x":127.083328,
         "y":180.416656
      },
      {  
         "x":127.500000,
         "y":177.916656
      },
      {  
         "x":127.500000,
         "y":177.500000
      },
      {  
         "x":127.500000,
         "y":175.833328
      },
      {  
         "x":127.500000,
         "y":175.416656
      },
      {  
         "x":127.500000,
         "y":175.000000
      },
      {  
         "x":127.500000,
         "y":174.583328
      },
      {  
         "x":127.500000,
         "y":171.666656
      },
      {  
         "x":127.500000,
         "y":170.000000
      },
      {  
         "x":127.500000,
         "y":168.750000
      },
      {  
         "x":127.500000,
         "y":167.083328
      },
      {  
         "x":127.500000,
         "y":166.250000
      },
      {  
         "x":127.500000,
         "y":164.166656
      },
      {  
         "x":127.500000,
         "y":163.333328
      },
      {  
         "x":127.500000,
         "y":162.916656
      },
      {  
         "x":127.500000,
         "y":162.500000
      },
      {  
         "x":127.500000,
         "y":160.833328
      },
      {  
         "x":127.500000,
         "y":160.000000
      },
      {  
         "x":127.500000,
         "y":158.333328
      },
      {  
         "x":127.500000,
         "y":157.916656
      },
      {  
         "x":127.500000,
         "y":157.083328
      },
      {  
         "x":127.500000,
         "y":156.666656
      },
      {  
         "x":127.500000,
         "y":155.000000
      },
      {  
         "x":127.500000,
         "y":154.583328
      },
      {  
         "x":127.500000,
         "y":153.750000
      },
      {  
         "x":127.500000,
         "y":151.666656
      },
      {  
         "x":127.500000,
         "y":149.166656
      },
      {  
         "x":127.500000,
         "y":147.916656
      },
      {  
         "x":127.500000,
         "y":146.250000
      },
      {  
         "x":127.500000,
         "y":145.833328
      },
      {  
         "x":127.500000,
         "y":145.416656
      },
      {  
         "x":127.083328,
         "y":145.000000
      },
      {  
         "x":127.083328,
         "y":143.333328
      },
      {  
         "x":127.083328,
         "y":142.500000
      },
      {  
         "x":127.083328,
         "y":142.083328
      },
      {  
         "x":127.083328,
         "y":140.000000
      },
      {  
         "x":127.083328,
         "y":139.583328
      },
      {  
         "x":127.083328,
         "y":139.166656
      },
      {  
         "x":127.083328,
         "y":137.083328
      },
      {  
         "x":127.083328,
         "y":136.250000
      },
      {  
         "x":127.083328,
         "y":134.166656
      },
      {  
         "x":127.083328,
         "y":133.333328
      },
      {  
         "x":127.083328,
         "y":131.250000
      },
      {  
         "x":127.083328,
         "y":130.416656
      },
      {  
         "x":127.083328,
         "y":130.000000
      },
      {  
         "x":127.083328,
         "y":128.333328
      },
      {  
         "x":127.083328,
         "y":127.500000
      },
      {  
         "x":127.083328,
         "y":127.083328
      },
      {  
         "x":127.083328,
         "y":125.416664
      },
      {  
         "x":127.083328,
         "y":125.000000
      },
      {  
         "x":127.083328,
         "y":124.166664
      },
      {  
         "x":127.083328,
         "y":122.500000
      },
      {  
         "x":127.083328,
         "y":121.250000
      },
      {  
         "x":127.083328,
         "y":119.583328
      },
      {  
         "x":127.083328,
         "y":118.333328
      },
      {  
         "x":127.500000,
         "y":116.666664
      },
      {  
         "x":127.500000,
         "y":115.833328
      },
      {  
         "x":127.500000,
         "y":115.000000
      },
      {  
         "x":127.500000,
         "y":113.750000
      },
      {  
         "x":127.500000,
         "y":112.083328
      },
      {  
         "x":127.500000,
         "y":110.833328
      },
      {  
         "x":127.500000,
         "y":110.000000
      },
      {  
         "x":127.500000,
         "y":109.166664
      },
      {  
         "x":127.500000,
         "y":107.916664
      },
      {  
         "x":127.500000,
         "y":107.500000
      },
      {  
         "x":127.500000,
         "y":106.666664
      },
      {  
         "x":127.500000,
         "y":106.250000
      },
      {  
         "x":127.083328,
         "y":105.000000
      },
      {  
         "x":127.500000,
         "y":104.166664
      },
      {  
         "x":127.083328,
         "y":104.166664
      },
      {  
         "x":127.083328,
         "y":103.750000
      },
      {  
         "x":126.666664,
         "y":102.083328
      },
      {  
         "x":126.250000,
         "y":101.666664
      },
      {  
         "x":126.250000,
         "y":101.250000
      },
      {  
         "x":126.250000,
         "y":100.416664
      },
      {  
         "x":125.833328,
         "y":99.166664
      },
      {  
         "x":125.416664,
         "y":98.750000
      },
      {  
         "x":125.416664,
         "y":98.333328
      },
      {  
         "x":124.583328,
         "y":96.250000
      },
      {  
         "x":117.916664,
         "y":93.333328
      },
      {  
         "x":115.416664,
         "y":95.000000
      },
      {  
         "x":114.583328,
         "y":95.416664
      },
      {  
         "x":113.333328,
         "y":96.666664
      },
      {  
         "x":112.916664,
         "y":97.083328
      },
      {  
         "x":112.500000,
         "y":97.500000
      },
      {  
         "x":111.250000,
         "y":99.166664
      },
      {  
         "x":110.833328,
         "y":99.583328
      },
      {  
         "x":109.583328,
         "y":100.833328
      },
      {  
         "x":109.166664,
         "y":101.666664
      },
      {  
         "x":108.750000,
         "y":102.083328
      },
      {  
         "x":107.916664,
         "y":103.333328
      },
      {  
         "x":107.500000,
         "y":103.750000
      },
      {  
         "x":107.083328,
         "y":104.166664
      },
      {  
         "x":105.833328,
         "y":106.250000
      },
      {  
         "x":104.583328,
         "y":107.916664
      },
      {  
         "x":104.166664,
         "y":108.750000
      },
      {  
         "x":102.916664,
         "y":111.666664
      },
      {  
         "x":104.166664,
         "y":116.250000
      },
      {  
         "x":104.583328,
         "y":116.666664
      },
      {  
         "x":106.250000,
         "y":117.500000
      },
      {  
         "x":106.250000,
         "y":117.916664
      },
      {  
         "x":106.250000,
         "y":118.333328
      },
      {  
         "x":106.666664,
         "y":118.750000
      },
      {  
         "x":108.333328,
         "y":119.166664
      },
      {  
         "x":108.750000,
         "y":119.166664
      },
      {  
         "x":111.250000,
         "y":119.583328
      },
      {  
         "x":111.666664,
         "y":119.583328
      },
      {  
         "x":112.083328,
         "y":119.583328
      },
      {  
         "x":114.583328,
         "y":120.000000
      },
      {  
         "x":112.916664,
         "y":119.583328
      },
      {  
         "x":114.583328,
         "y":120.000000
      },
      {  
         "x":115.000000,
         "y":120.000000
      },
      {  
         "x":115.416664,
         "y":120.000000
      },
      {  
         "x":115.833328,
         "y":120.000000
      },
      {  
         "x":117.500000,
         "y":120.000000
      },
      {  
         "x":118.333328,
         "y":120.000000
      },
      {  
         "x":118.750000,
         "y":120.000000
      },
      {  
         "x":120.416664,
         "y":120.000000
      },
      {  
         "x":205.000000,
         "y":189.166656
      },
      {  
         "x":205.833328,
         "y":186.250000
      },
      {  
         "x":205.833328,
         "y":185.416656
      },
      {  
         "x":205.833328,
         "y":185.000000
      },
      {  
         "x":205.833328,
         "y":183.333328
      },
      {  
         "x":205.833328,
         "y":182.083328
      },
      {  
         "x":205.833328,
         "y":180.416656
      },
      {  
         "x":205.833328,
         "y":179.166656
      },
      {  
         "x":205.833328,
         "y":177.500000
      },
      {  
         "x":205.833328,
         "y":170.416656
      },
      {  
         "x":205.833328,
         "y":168.750000
      },
      {  
         "x":205.833328,
         "y":167.500000
      },
      {  
         "x":205.833328,
         "y":165.416656
      },
      {  
         "x":205.833328,
         "y":162.916656
      },
      {  
         "x":205.833328,
         "y":161.250000
      },
      {  
         "x":205.833328,
         "y":158.333328
      },
      {  
         "x":205.833328,
         "y":156.250000
      },
      {  
         "x":205.833328,
         "y":155.416656
      },
      {  
         "x":205.833328,
         "y":152.916656
      },
      {  
         "x":205.833328,
         "y":150.833328
      },
      {  
         "x":205.833328,
         "y":149.166656
      },
      {  
         "x":205.833328,
         "y":147.916656
      },
      {  
         "x":205.833328,
         "y":146.250000
      },
      {  
         "x":205.833328,
         "y":144.583328
      },
      {  
         "x":205.833328,
         "y":143.333328
      },
      {  
         "x":205.833328,
         "y":142.083328
      },
      {  
         "x":205.833328,
         "y":141.666656
      },
      {  
         "x":205.833328,
         "y":141.250000
      },
      {  
         "x":205.833328,
         "y":140.416656
      },
      {  
         "x":205.833328,
         "y":138.333328
      },
      {  
         "x":205.833328,
         "y":135.833328
      },
      {  
         "x":205.833328,
         "y":134.583328
      },
      {  
         "x":205.833328,
         "y":132.916656
      },
      {  
         "x":205.833328,
         "y":132.500000
      },
      {  
         "x":205.833328,
         "y":131.666656
      },
      {  
         "x":205.833328,
         "y":130.000000
      },
      {  
         "x":205.833328,
         "y":129.166656
      },
      {  
         "x":205.833328,
         "y":128.750000
      },
      {  
         "x":205.833328,
         "y":127.083328
      },
      {  
         "x":205.833328,
         "y":126.666664
      },
      {  
         "x":205.833328,
         "y":125.833328
      },
      {  
         "x":205.833328,
         "y":123.333328
      },
      {  
         "x":205.833328,
         "y":122.500000
      },
      {  
         "x":205.833328,
         "y":120.833328
      },
      {  
         "x":205.833328,
         "y":120.416664
      },
      {  
         "x":205.833328,
         "y":119.583328
      },
      {  
         "x":205.833328,
         "y":118.333328
      },
      {  
         "x":205.833328,
         "y":115.416664
      },
      {  
         "x":205.833328,
         "y":113.750000
      },
      {  
         "x":205.833328,
         "y":112.500000
      },
      {  
         "x":205.833328,
         "y":110.833328
      },
      {  
         "x":205.833328,
         "y":109.166664
      },
      {  
         "x":205.833328,
         "y":108.750000
      },
      {  
         "x":205.833328,
         "y":107.916664
      },
      {  
         "x":205.833328,
         "y":106.250000
      },
      {  
         "x":205.833328,
         "y":105.000000
      },
      {  
         "x":205.833328,
         "y":103.333328
      },
      {  
         "x":205.833328,
         "y":102.083328
      },
      {  
         "x":205.833328,
         "y":100.416664
      },
      {  
         "x":205.833328,
         "y":100.000000
      },
      {  
         "x":205.833328,
         "y":99.166664
      },
      {  
         "x":205.833328,
         "y":98.750000
      },
      {  
         "x":205.833328,
         "y":97.500000
      },
      {  
         "x":205.833328,
         "y":97.083328
      },
      {  
         "x":205.833328,
         "y":95.833328
      },
      {  
         "x":205.833328,
         "y":94.583328
      },
      {  
         "x":205.833328,
         "y":93.750000
      },
      {  
         "x":205.833328,
         "y":92.916664
      },
      {  
         "x":205.833328,
         "y":91.666664
      },
      {  
         "x":206.250000,
         "y":91.666664
      },
      {  
         "x":206.250000,
         "y":91.250000
      },
      {  
         "x":206.250000,
         "y":90.000000
      },
      {  
         "x":206.250000,
         "y":88.750000
      },
      {  
         "x":206.250000,
         "y":87.916664
      },
      {  
         "x":206.250000,
         "y":87.083328
      },
      {  
         "x":206.250000,
         "y":85.416664
      },
      {  
         "x":206.250000,
         "y":84.583328
      },
      {  
         "x":206.250000,
         "y":84.166664
      },
      {  
         "x":206.250000,
         "y":82.500000
      },
      {  
         "x":206.250000,
         "y":82.083328
      },
      {  
         "x":206.666656,
         "y":81.250000
      },
      {  
         "x":206.666656,
         "y":78.750000
      },
      {  
         "x":206.666656,
         "y":76.666664
      },
      {  
         "x":206.666656,
         "y":75.833328
      },
      {  
         "x":206.666656,
         "y":75.416664
      },
      {  
         "x":206.666656,
         "y":73.333328
      },
      {  
         "x":206.666656,
         "y":72.500000
      },
      {  
         "x":206.250000,
         "y":72.083328
      },
      {  
         "x":206.666656,
         "y":70.000000
      },
      {  
         "x":206.666656,
         "y":69.583328
      },
      {  
         "x":206.250000,
         "y":67.916664
      },
      {  
         "x":206.666656,
         "y":67.500000
      },
      {  
         "x":206.666656,
         "y":66.666664
      },
      {  
         "x":206.666656,
         "y":64.583328
      },
      {  
         "x":206.666656,
         "y":63.750000
      },
      {  
         "x":206.666656,
         "y":61.666664
      },
      {  
         "x":206.666656,
         "y":61.250000
      },
      {  
         "x":206.666656,
         "y":60.416664
      },
      {  
         "x":206.666656,
         "y":58.750000
      },
      {  
         "x":206.666656,
         "y":58.333332
      },
      {  
         "x":206.666656,
         "y":57.916664
      },
      {  
         "x":206.666656,
         "y":57.500000
      },
      {  
         "x":206.666656,
         "y":55.833332
      },
      {  
         "x":206.666656,
         "y":55.416664
      },
      {  
         "x":206.666656,
         "y":55.000000
      },
      {  
         "x":206.666656,
         "y":54.583332
      },
      {  
         "x":206.666656,
         "y":52.083332
      },
      {  
         "x":206.666656,
         "y":51.666664
      },
      {  
         "x":206.666656,
         "y":46.666664
      },
      {  
         "x":206.666656,
         "y":45.833332
      },
      {  
         "x":206.666656,
         "y":43.750000
      },
      {  
         "x":83.750000,
         "y":190.000000
      },
      {  
         "x":84.583328,
         "y":190.000000
      },
      {  
         "x":85.000000,
         "y":190.000000
      },
      {  
         "x":86.666664,
         "y":190.000000
      },
      {  
         "x":87.083328,
         "y":190.000000
      },
      {  
         "x":87.500000,
         "y":190.000000
      },
      {  
         "x":87.916664,
         "y":190.000000
      },
      {  
         "x":89.583328,
         "y":190.000000
      },
      {  
         "x":90.000000,
         "y":190.000000
      },
      {  
         "x":90.833328,
         "y":190.000000
      },
      {  
         "x":92.500000,
         "y":190.000000
      },
      {  
         "x":92.916664,
         "y":190.000000
      },
      {  
         "x":93.333328,
         "y":190.000000
      },
      {  
         "x":95.833328,
         "y":190.000000
      },
      {  
         "x":96.250000,
         "y":190.000000
      },
      {  
         "x":98.750000,
         "y":190.000000
      },
      {  
         "x":99.583328,
         "y":190.000000
      },
      {  
         "x":101.666664,
         "y":190.000000
      },
      {  
         "x":105.833328,
         "y":190.000000
      },
      {  
         "x":110.416664,
         "y":190.000000
      },
      {  
         "x":113.333328,
         "y":190.000000
      },
      {  
         "x":114.166664,
         "y":190.000000
      },
      {  
         "x":114.583328,
         "y":190.000000
      },
      {  
         "x":116.250000,
         "y":190.000000
      },
      {  
         "x":117.500000,
         "y":190.000000
      },
      {  
         "x":120.416664,
         "y":190.000000
      },
      {  
         "x":122.500000,
         "y":190.000000
      },
      {  
         "x":123.333328,
         "y":190.000000
      },
      {  
         "x":125.416664,
         "y":190.000000
      },
      {  
         "x":125.833328,
         "y":190.000000
      },
      {  
         "x":128.333328,
         "y":190.000000
      },
      {  
         "x":129.166656,
         "y":190.000000
      },
      {  
         "x":132.083328,
         "y":190.000000
      },
      {  
         "x":134.166656,
         "y":190.000000
      },
      {  
         "x":135.416656,
         "y":190.000000
      },
      {  
         "x":137.083328,
         "y":190.000000
      },
      {  
         "x":138.333328,
         "y":190.000000
      },
      {  
         "x":141.250000,
         "y":190.000000
      },
      {  
         "x":144.166656,
         "y":190.000000
      },
      {  
         "x":147.083328,
         "y":190.000000
      },
      {  
         "x":149.583328,
         "y":190.000000
      },
      {  
         "x":150.000000,
         "y":190.000000
      },
      {  
         "x":150.416656,
         "y":189.583328
      },
      {  
         "x":151.666656,
         "y":189.583328
      },
      {  
         "x":153.333328,
         "y":189.583328
      },
      {  
         "x":156.250000,
         "y":190.000000
      },
      {  
         "x":159.166656,
         "y":190.000000
      },
      {  
         "x":163.750000,
         "y":190.000000
      },
      {  
         "x":165.000000,
         "y":190.000000
      },
      {  
         "x":166.666656,
         "y":190.000000
      },
      {  
         "x":168.333328,
         "y":189.583328
      },
      {  
         "x":172.500000,
         "y":189.583328
      },
      {  
         "x":174.166656,
         "y":189.583328
      },
      {  
         "x":175.416656,
         "y":189.583328
      },
      {  
         "x":176.250000,
         "y":190.000000
      },
      {  
         "x":178.333328,
         "y":189.583328
      },
      {  
         "x":178.750000,
         "y":190.000000
      },
      {  
         "x":179.583328,
         "y":190.000000
      },
      {  
         "x":180.000000,
         "y":189.583328
      },
      {  
         "x":182.083328,
         "y":190.000000
      },
      {  
         "x":185.833328,
         "y":190.000000
      },
      {  
         "x":187.916656,
         "y":190.000000
      },
      {  
         "x":188.750000,
         "y":190.000000
      },
      {  
         "x":190.833328,
         "y":190.000000
      },
      {  
         "x":191.666656,
         "y":190.000000
      },
      {  
         "x":193.333328,
         "y":189.583328
      },
      {  
         "x":194.583328,
         "y":190.000000
      },
      {  
         "x":197.083328,
         "y":190.000000
      },
      {  
         "x":199.583328,
         "y":190.000000
      },
      {  
         "x":202.916656,
         "y":190.000000
      },
      {  
         "x":205.416656,
         "y":190.000000
      },
      {  
         "x":206.666656,
         "y":190.000000
      },
      {  
         "x":208.333328,
         "y":190.000000
      },
      {  
         "x":208.750000,
         "y":190.000000
      },
      {  
         "x":209.166656,
         "y":190.000000
      },
      {  
         "x":211.666656,
         "y":190.000000
      },
      {  
         "x":214.166656,
         "y":190.000000
      },
      {  
         "x":215.416656,
         "y":190.000000
      },
      {  
         "x":217.083328,
         "y":190.000000
      },
      {  
         "x":220.416656,
         "y":190.000000
      },
      {  
         "x":223.333328,
         "y":190.000000
      },
      {  
         "x":224.166656,
         "y":190.000000
      },
      {  
         "x":226.666656,
         "y":190.000000
      },
      {  
         "x":229.583328,
         "y":190.000000
      },
      {  
         "x":230.416656,
         "y":189.583328
      },
      {  
         "x":233.333328,
         "y":190.000000
      },
      {  
         "x":235.000000,
         "y":190.000000
      },
      {  
         "x":235.833328,
         "y":190.000000
      },
      {  
         "x":236.250000,
         "y":190.000000
      },
      {  
         "x":237.916656,
         "y":190.000000
      },
      {  
         "x":238.333328,
         "y":190.000000
      },
      {  
         "x":238.750000,
         "y":190.000000
      },
      {  
         "x":239.166656,
         "y":190.000000
      },
      {  
         "x":240.833328,
         "y":190.000000
      }
   ]
}