{
  "points": [
    {
      "x": 51.25,
      "y": 179.166656
    },
    {
      "x": 51.666664,
      "y": 179.166656
    },
    {
      "x": 52.083332,
      "y": 178.75
    },
    {
      "x": 52.916664,
      "y": 177.916656
    },
    {
      "x": 53.333332,
      "y": 177.5
    },
    {
      "x": 53.75,
      "y": 177.083328
    },
    {
      "x": 55.833332,
      "y": 174.583328
    },
    {
      "x": 56.666664,
      "y": 174.166656
    },
    {
      "x": 57.083332,
      "y": 173.75
    },
    {
      "x": 57.5,
      "y": 173.333328
    },
    {
      "x": 57.916664,
      "y": 172.916656
    },
    {
      "x": 58.333332,
      "y": 172.5
    },
    {
      "x": 58.75,
      "y": 172.083328
    },
    {
      "x": 59.166664,
      "y": 171.25
    },
    {
      "x": 60.833332,
      "y": 169.583328
    },
    {
      "x": 61.666664,
      "y": 169.166656
    },
    {
      "x": 62.083332,
      "y": 168.75
    },
    {
      "x": 62.5,
      "y": 168.333328
    },
    {
      "x": 63.333332,
      "y": 167.5
    },
    {
      "x": 63.75,
      "y": 167.083328
    },
    {
      "x": 65.833328,
      "y": 164.583328
    },
    {
      "x": 66.666664,
      "y": 164.166656
    },
    {
      "x": 67.5,
      "y": 163.333328
    },
    {
      "x": 68.333328,
      "y": 162.5
    },
    {
      "x": 69.166664,
      "y": 161.25
    },
    {
      "x": 70.833328,
      "y": 159.583328
    },
    {
      "x": 71.666664,
      "y": 159.166656
    },
    {
      "x": 72.5,
      "y": 158.333328
    },
    {
      "x": 72.916664,
      "y": 157.083328
    },
    {
      "x": 73.75,
      "y": 156.666656
    },
    {
      "x": 74.166664,
      "y": 156.25
    },
    {
      "x": 75.416664,
      "y": 154.166656
    },
    {
      "x": 76.25,
      "y": 153.333328
    },
    {
      "x": 76.666664,
      "y": 153.333328
    },
    {
      "x": 76.666664,
      "y": 152.5
    },
    {
      "x": 77.083328,
      "y": 152.5
    },
    {
      "x": 77.083328,
      "y": 152.083328
    },
    {
      "x": 77.5,
      "y": 151.25
    },
    {
      "x": 78.333328,
      "y": 151.25
    },
    {
      "x": 78.333328,
      "y": 150.416656
    },
    {
      "x": 79.166664,
      "y": 150.833328
    },
    {
      "x": 80.416664,
      "y": 148.75
    },
    {
      "x": 81.25,
      "y": 148.333328
    },
    {
      "x": 82.5,
      "y": 147.083328
    },
    {
      "x": 83.75,
      "y": 146.666656
    },
    {
      "x": 84.166664,
      "y": 145.833328
    },
    {
      "x": 85.416664,
      "y": 144.166656
    },
    {
      "x": 85.833328,
      "y": 144.166656
    },
    {
      "x": 85.833328,
      "y": 143.75
    },
    {
      "x": 87.083328,
      "y": 143.75
    },
    {
      "x": 87.083328,
      "y": 142.5
    },
    {
      "x": 87.916664,
      "y": 142.5
    },
    {
      "x": 87.916664,
      "y": 142.083328
    },
    {
      "x": 88.75,
      "y": 142.083328
    },
    {
      "x": 89.166664,
      "y": 141.25
    },
    {
      "x": 89.166664,
      "y": 140.833328
    },
    {
      "x": 90.833328,
      "y": 139.166656
    },
    {
      "x": 91.25,
      "y": 139.166656
    },
    {
      "x": 91.25,
      "y": 138.75
    },
    {
      "x": 91.666664,
      "y": 138.75
    },
    {
      "x": 92.083328,
      "y": 138.333328
    },
    {
      "x": 92.916664,
      "y": 137.916656
    },
    {
      "x": 93.333328,
      "y": 137.5
    },
    {
      "x": 93.75,
      "y": 136.666656
    },
    {
      "x": 94.166664,
      "y": 136.666656
    },
    {
      "x": 94.166664,
      "y": 136.25
    },
    {
      "x": 94.166664,
      "y": 135.833328
    },
    {
      "x": 95.833328,
      "y": 134.166656
    },
    {
      "x": 96.666664,
      "y": 134.166656
    },
    {
      "x": 97.083328,
      "y": 133.75
    },
    {
      "x": 97.916664,
      "y": 132.916656
    },
    {
      "x": 98.75,
      "y": 132.083328
    },
    {
      "x": 99.166664,
      "y": 131.666656
    },
    {
      "x": 101.666664,
      "y": 129.166656
    },
    {
      "x": 102.5,
      "y": 128.333328
    },
    {
      "x": 102.916664,
      "y": 127.916664
    },
    {
      "x": 103.333328,
      "y": 127.5
    },
    {
      "x": 103.75,
      "y": 127.083328
    },
    {
      "x": 104.166664,
      "y": 126.666664
    },
    {
      "x": 106.666664,
      "y": 124.166664
    },
    {
      "x": 107.5,
      "y": 123.333328
    },
    {
      "x": 107.916664,
      "y": 122.916664
    },
    {
      "x": 108.333328,
      "y": 122.5
    },
    {
      "x": 109.166664,
      "y": 121.666664
    },
    {
      "x": 111.25,
      "y": 119.166664
    },
    {
      "x": 112.083328,
      "y": 118.75
    },
    {
      "x": 112.5,
      "y": 118.333328
    },
    {
      "x": 112.916664,
      "y": 117.916664
    },
    {
      "x": 113.333328,
      "y": 117.5
    },
    {
      "x": 113.75,
      "y": 117.083328
    },
    {
      "x": 114.166664,
      "y": 116.666664
    },
    {
      "x": 116.25,
      "y": 114.166664
    },
    {
      "x": 117.083328,
      "y": 113.75
    },
    {
      "x": 117.5,
      "y": 113.333328
    },
    {
      "x": 117.916664,
      "y": 112.916664
    },
    {
      "x": 118.75,
      "y": 112.083328
    },
    {
      "x": 119.166664,
      "y": 111.666664
    },
    {
      "x": 121.25,
      "y": 109.166664
    },
    {
      "x": 122.083328,
      "y": 108.75
    },
    {
      "x": 122.916664,
      "y": 107.916664
    },
    {
      "x": 123.75,
      "y": 107.083328
    },
    {
      "x": 124.166664,
      "y": 106.666664
    },
    {
      "x": 127.083328,
      "y": 103.75
    },
    {
      "x": 127.5,
      "y": 103.333328
    },
    {
      "x": 128.333328,
      "y": 102.5
    },
    {
      "x": 129.166656,
      "y": 101.666664
    },
    {
      "x": 132.083328,
      "y": 98.75
    },
    {
      "x": 132.5,
      "y": 98.333328
    },
    {
      "x": 132.916656,
      "y": 97.916664
    },
    {
      "x": 134.166656,
      "y": 96.666664
    },
    {
      "x": 137.083328,
      "y": 93.75
    },
    {
      "x": 137.5,
      "y": 93.333328
    },
    {
      "x": 138.75,
      "y": 92.083328
    },
    {
      "x": 139.166656,
      "y": 91.666664
    },
    {
      "x": 142.083328,
      "y": 88.75
    },
    {
      "x": 142.916656,
      "y": 87.916664
    },
    {
      "x": 144.166656,
      "y": 86.666664
    },
    {
      "x": 147.083328,
      "y": 83.75
    },
    {
      "x": 147.5,
      "y": 83.333328
    },
    {
      "x": 148.333328,
      "y": 82.5
    },
    {
      "x": 148.75,
      "y": 82.083328
    },
    {
      "x": 149.166656,
      "y": 81.666664
    },
    {
      "x": 152.083328,
      "y": 78.75
    },
    {
      "x": 152.5,
      "y": 78.333328
    },
    {
      "x": 153.333328,
      "y": 77.5
    },
    {
      "x": 153.75,
      "y": 77.083328
    },
    {
      "x": 154.166656,
      "y": 76.666664
    },
    {
      "x": 157.083328,
      "y": 73.75
    },
    {
      "x": 157.5,
      "y": 73.333328
    },
    {
      "x": 157.916656,
      "y": 72.916664
    },
    {
      "x": 158.333328,
      "y": 72.5
    },
    {
      "x": 158.75,
      "y": 72.083328
    },
    {
      "x": 159.166656,
      "y": 71.666664
    },
    {
      "x": 162.083328,
      "y": 68.75
    },
    {
      "x": 162.5,
      "y": 68.333328
    },
    {
      "x": 162.916656,
      "y": 67.916664
    },
    {
      "x": 163.333328,
      "y": 67.5
    },
    {
      "x": 164.166656,
      "y": 66.666664
    },
    {
      "x": 167.083328,
      "y": 63.75
    },
    {
      "x": 167.5,
      "y": 63.333332
    },
    {
      "x": 168.333328,
      "y": 62.5
    },
    {
      "x": 168.75,
      "y": 62.083332
    },
    {
      "x": 169.166656,
      "y": 61.666664
    },
    {
      "x": 169.583328,
      "y": 61.25
    },
    {
      "x": 172.083328,
      "y": 58.75
    },
    {
      "x": 172.5,
      "y": 58.333332
    },
    {
      "x": 173.333328,
      "y": 57.5
    },
    {
      "x": 173.75,
      "y": 57.083332
    },
    {
      "x": 174.166656,
      "y": 56.666664
    },
    {
      "x": 174.583328,
      "y": 56.25
    },
    {
      "x": 177.083328,
      "y": 53.75
    }
  ]
}