{
  "name": "color_set3_large",
    "type": "color",
    "suffix": "color_set3_large_",
    "objectList": [{
      "objectId": "color_set3_large_black",
      "imageUri": "common/colors/color_set3/color_set3_large/color_set3_large_black.png",
      "name": "color_black",
      "color": "color_black",
      "colorcode": "000000",
      "h": 79.61,
      "w": 55.43
    }, {
      "objectId": "color_set3_large_blue",
      "imageUri": "common/colors/color_set3/color_set3_large/color_set3_large_blue.png",
      "name": "color_blue",
      "color": "color_blue",
      "colorcode": "175eab",
      "h": 68.77,
      "w": 53.35
    }, {
      "objectId": "color_set3_large_brown",
      "imageUri": "common/colors/color_set3/color_set3_large/color_set3_large_brown.png",
      "name": "color_brown",
      "color": "color_brown",
      "colorcode": "603813",
      "h": 72.94,
      "w": 62.1
    }, {
      "objectId": "color_set3_large_cyan",
        "imageUri": "common/colors/color_set3/color_set3_large/color_set3_large_cyan.png",
        "name": "color_cyan",
        "color": "color_cyan",
        "colorcode": "0eb1dd",
        "h": 73.36,
        "w": 80.03
    }, {
      "objectId": "color_set3_large_green",
        "imageUri": "common/colors/color_set3/color_set3_large/color_set3_large_green.png",
        "name": "color_green",
        "color": "color_green",
        "colorcode": "0b9444",
        "h": 78.36,
        "w": 54.6
    }, {
      "objectId": "color_set3_large_grey",
        "imageUri": "common/colors/color_set3/color_set3_large/color_set3_large_grey.png",
        "name": "color_grey",
        "color": "color_grey",
        "colorcode": "939598",
        "h": 71.69,
        "w": 78.36
    }, {
      "objectId": "color_set3_large_orange",
        "imageUri": "common/colors/color_set3/color_set3_large/color_set3_large_orange.png",
        "name": "color_orange",
        "color": "color_orange",
        "colorcode": "f1592a",
        "h": 72.52,
        "w": 57.94
    }, {
      "objectId": "color_set3_large_pink",
        "imageUri": "common/colors/color_set3/color_set3_large/color_set3_large_pink.png",
        "name": "color_pink",
        "color": "color_pink",
        "colorcode": "e959a1",
        "h": 62.94,
        "w": 77.52
    }, {
      "objectId": "color_set3_large_purple",
        "imageUri": "common/colors/color_set3/color_set3_large/color_set3_large_purple.png",
        "name": "color_purple",
        "color": "color_purple",
        "colorcode": "662d91",
        "h": 80.44,
        "w": 66.27
    }, {
      "objectId": "color_set3_large_red",
        "imageUri": "common/colors/color_set3/color_set3_large/color_set3_large_red.png",
        "name": "color_red",
        "color": "color_red",
        "colorcode": "df242a",
        "h": 77.11,
        "w": 53.35
    }, {
      "objectId": "color_set3_large_white",
        "imageUri": "common/colors/color_set3/color_set3_large/color_set3_large_white.png",
        "name": "color_white",
        "color": "color_white",
        "colorcode": "ffffff",
        "h": 80.03,
        "w": 68.36
    }, {
      "objectId": "color_set3_large_yellow",
        "imageUri": "common/colors/color_set3/color_set3_large/color_set3_large_yellow.png",
        "name": "color_yellow",
        "color": "color_yellow",
        "colorcode": "fff200",
        "h": 70.02,
        "w": 74.61
    }]
}
