{
    "name": "habitat_set2_x_large",
    "type": "",
    "suffix": "habitat_set2_x_large_",
    "objectList": [
                {
                    "objectId": "habitat_set2_x_large_barn",
                    "name": "animal_cow",
                    "imageUri": "common/habitat/habitat_set2/habitat_set2_x_large/habitat_set2_x_large_barn.png",
                    "w": 133.376,
                    "h": 108.785,
                    "shape": "",
                    "color": ""
                },
                {
                    "objectId": "habitat_set2_x_large_cave",
                    "name": "animal_lion",
                    "imageUri": "common/habitat/habitat_set2/habitat_set2_x_large/habitat_set2_x_large_cave.png",
                    "w": 133.376,
                    "h": 75.441,
                    "shape": "",
                    "color": ""
                },
                {
                    "objectId": "habitat_set2_x_large_fence",
                    "name": "animal_sheep",
                    "imageUri": "common/habitat/habitat_set2/habitat_set2_x_large/habitat_set2_x_large_fence.png",
                    "w": 131.292,
                    "h": 88.362,
                    "shape": "",
                    "color": ""
                },
                {
                    "objectId": "habitat_set2_x_large_forest",
                    "name": "animal_elephant",
                    "imageUri": "common/habitat/habitat_set2/habitat_set2_x_large/habitat_set2_x_large_forest.png",
                    "w": 133.376,
                    "h": 102.95,
                    "shape": "",
                    "color": ""
                },
                {
                    "objectId": "habitat_set2_x_large_kennel",
                    "name": "animal_dog",
                    "imageUri": "common/habitat/habitat_set2/habitat_set2_x_large/habitat_set2_x_large_kennel.png",
                    "w": 112.119,
                    "h": 130.875,
                    "shape": "",
                    "color": ""
                },
                {
                    "objectId": "habitat_set2_x_large_marsh",
                    "name": "animal_rhino",
                    "imageUri": "common/habitat/habitat_set2/habitat_set2_x_large/habitat_set2_x_large_marsh.png",
                    "w": 132.959,
                    "h": 105.45,
                    "shape": "",
                    "color": ""
                },
                {
                    "objectId": "habitat_set2_x_large_mouse_hole",
                    "name": "animal_mouse",
                    "imageUri": "common/habitat/habitat_set2/habitat_set2_x_large/habitat_set2_x_large_mouse_hole.png",
                    "w": 131.709,
                    "h": 68.355,
                    "shape": "",
                    "color": ""
                },
                {
                    "objectId": "habitat_set2_x_large_pillow",
                    "name": "animal_cat",
                    "imageUri": "common/habitat/habitat_set2/habitat_set2_x_large/habitat_set2_x_large_pillow.png",
                    "w": 133.793,
                    "h": 76.691,
                    "shape": "",
                    "color": ""
                },
                {
                    "objectId": "habitat_set2_x_large_puddle",
                    "name": "animal_pig",
                    "imageUri": "common/habitat/habitat_set2/habitat_set2_x_large/habitat_set2_x_large_puddle.png",
                    "w": 132.542,
                    "h": 86.278,
                    "shape": "",
                    "color": ""
                },
                {
                    "objectId": "habitat_set2_x_large_rabbit_hole",
                    "name": "animal_rabbit",
                    "imageUri": "common/habitat/habitat_set2/habitat_set2_x_large/habitat_set2_x_large_rabbit_hole.png",
                    "w": 132.959,
                    "h": 90.862,
                    "shape": "",
                    "color": ""
                }
            ]
}