{
    "name": "number_set14_x_large",
    "type": "number",
    "suffix": "number_set14_x_large_",
    "objectList": [
        {
            "objectId": "number_set14_x_large_0",
            "name": "number_0",
            "imageUri": "common/numbers/number_set14/number_set14_x_large/number_set14_x_large_0.png",
            "w": 100.449,
            "h": 133.376,
            "shape": "",
            "color": ""
        },
        {
            "objectId": "number_set14_x_large_1",
            "name": "number_1",
            "imageUri": "common/numbers/number_set14/number_set14_x_large/number_set14_x_large_1.png",
            "w": 82.526,
            "h": 133.376,
            "shape": "",
            "color": ""
        },
        {
            "objectId": "number_set14_x_large_2",
            "name": "number_2",
            "imageUri": "common/numbers/number_set14/number_set14_x_large/number_set14_x_large_2.png",
            "w": 80.859,
            "h": 133.376,
            "shape": "",
            "color": ""
        },
        {
            "objectId": "number_set14_x_large_3",
            "name": "number_3",
            "imageUri": "common/numbers/number_set14/number_set14_x_large/number_set14_x_large_3.png",
            "w": 76.274,
            "h": 133.376,
            "shape": "",
            "color": ""
        },
        {
            "objectId": "number_set14_x_large_4",
            "name": "number_4",
            "imageUri": "common/numbers/number_set14/number_set14_x_large/number_set14_x_large_4.png",
            "w": 95.03,
            "h": 133.793,
            "shape": "",
            "color": ""
        },
        {
            "objectId": "number_set14_x_large_5",
            "name": "number_5",
            "imageUri": "common/numbers/number_set14/number_set14_x_large/number_set14_x_large_5.png",
            "w": 91.696,
            "h": 133.376,
            "shape": "",
            "color": ""
        },
        {
            "objectId": "number_set14_x_large_6",
            "name": "number_6",
            "imageUri": "common/numbers/number_set14/number_set14_x_large/number_set14_x_large_6.png",
            "w": 101.699,
            "h": 133.793,
            "shape": "",
            "color": ""
        },
        {
            "objectId": "number_set14_x_large_7",
            "name": "number_7",
            "imageUri": "common/numbers/number_set14/number_set14_x_large/number_set14_x_large_7.png",
            "w": 80.026,
            "h": 132.959,
            "shape": "",
            "color": ""
        },
        {
            "objectId": "number_set14_x_large_8",
            "name": "number_8",
            "imageUri": "common/numbers/number_set14/number_set14_x_large/number_set14_x_large_8.png",
            "w": 92.53,
            "h": 133.793,
            "shape": "",
            "color": ""
        },
        {
            "objectId": "number_set14_x_large_9",
            "name": "number_9",
            "imageUri": "common/numbers/number_set14/number_set14_x_large/number_set14_x_large_9.png",
            "w": 97.531,
            "h": 133.793,
            "shape": "",
            "color": ""
        }
    ]
}
